generative/__init__.py
generative/version.py
generative/engines/__init__.py
generative/engines/prepare_batch.py
generative/engines/trainer.py
generative/inferers/__init__.py
generative/inferers/inferer.py
generative/losses/__init__.py
generative/losses/adversarial_loss.py
generative/losses/perceptual.py
generative/losses/spectral_loss.py
generative/metrics/__init__.py
generative/metrics/fid.py
generative/metrics/mmd.py
generative/metrics/ms_ssim.py
generative/metrics/ssim.py
generative/networks/__init__.py
generative/networks/blocks/__init__.py
generative/networks/blocks/encoder_modules.py
generative/networks/blocks/selfattention.py
generative/networks/blocks/spade_norm.py
generative/networks/blocks/transformerblock.py
generative/networks/layers/__init__.py
generative/networks/layers/vector_quantizer.py
generative/networks/nets/__init__.py
generative/networks/nets/autoencoderkl.py
generative/networks/nets/controlnet.py
generative/networks/nets/diffusion_model_unet.py
generative/networks/nets/patchgan_discriminator.py
generative/networks/nets/spade_autoencoderkl.py
generative/networks/nets/spade_diffusion_model_unet.py
generative/networks/nets/spade_network.py
generative/networks/nets/transformer.py
generative/networks/nets/vqvae.py
generative/networks/schedulers/__init__.py
generative/networks/schedulers/ddim (Mark Graham's conflicted copy 2024-01-08).py
generative/networks/schedulers/ddim.py
generative/networks/schedulers/ddpm.py
generative/networks/schedulers/pndm.py
generative/networks/schedulers/scheduler.py
generative/utils/__init__.py
generative/utils/component_store.py
generative/utils/enums.py
generative/utils/misc.py
generative/utils/ordering.py
tests/__init__.py
tests/min_tests.py
tests/runner.py
tests/test_adversarial.py
tests/test_autoencoderkl.py
tests/test_component_store.py
tests/test_compute_fid_metric.py
tests/test_compute_mmd_metric.py
tests/test_compute_multiscalessim_metric.py
tests/test_controlnet.py
tests/test_controlnet_inferers.py
monai_generative-0.2.3.dist-info/LICENSE
monai_generative-0.2.3.dist-info/METADATA
monai_generative-0.2.3.dist-info/WHEEL
monai_generative-0.2.3.dist-info/top_level.txt
monai_generative-0.2.3.dist-info/RECORD
